[
  {
    "inputs": [],
    "stateMutability": "nonpayable",
    "type": "constructor"
  },
  {
    "anonymous": false,
    "inputs": [
      {
        "indexed": true,
        "internalType": "address",
        "name": "previousOwner",
        "type": "address"
      },
      {
        "indexed": true,
        "internalType": "address",
        "name": "newOwner",
        "type": "address"
      }
    ],
    "name": "OwnershipTransferred",
    "type": "event"
  },
  {
    "anonymous": false,
    "inputs": [
      {
        "indexed": true,
        "internalType": "address",
        "name": "account",
        "type": "address"
      },
      {
        "indexed": false,
        "internalType": "uint256",
        "name": "chapterId",
        "type": "uint256"
      },
      {
        "indexed": false,
        "internalType": "uint256",
        "name": "voteId",
        "type": "uint256"
      },
      {
        "indexed": false,
        "internalType": "uint256",
        "name": "amount",
        "type": "uint256"
      },
      {
        "indexed": false,
        "internalType": "uint256",
        "name": "tokenAmount",
        "type": "uint256"
      }
    ],
    "name": "ProducerPassStaked",
    "type": "event"
  },
  {
    "anonymous": false,
    "inputs": [
      {
        "indexed": true,
        "internalType": "address",
        "name": "account",
        "type": "address"
      },
      {
        "indexed": false,
        "internalType": "uint256",
        "name": "chapterId",
        "type": "uint256"
      },
      {
        "indexed": false,
        "internalType": "uint256",
        "name": "voteId",
        "type": "uint256"
      }
    ],
    "name": "ProducerPassUnstaked",
    "type": "event"
  },
  {
    "inputs": [
      {
        "internalType": "uint256",
        "name": "",
        "type": "uint256"
      }
    ],
    "name": "chapters",
    "outputs": [
      {
        "internalType": "uint256",
        "name": "",
        "type": "uint256"
      }
    ],
    "stateMutability": "view",
    "type": "function"
  },
  {
    "inputs": [],
    "name": "documentaryProducerPass",
    "outputs": [
      {
        "internalType": "contract DocumentaryProducerPass",
        "name": "",
        "type": "address"
      }
    ],
    "stateMutability": "view",
    "type": "function"
  },
  {
    "inputs": [],
    "name": "documentaryToken",
    "outputs": [
      {
        "internalType": "contract Token",
        "name": "",
        "type": "address"
      }
    ],
    "stateMutability": "view",
    "type": "function"
  },
  {
    "inputs": [
      {
        "internalType": "uint256",
        "name": "chapterId",
        "type": "uint256"
      },
      {
        "internalType": "uint256",
        "name": "amount",
        "type": "uint256"
      }
    ],
    "name": "getTokenAllocationForStaking",
    "outputs": [
      {
        "internalType": "uint256",
        "name": "",
        "type": "uint256"
      }
    ],
    "stateMutability": "view",
    "type": "function"
  },
  {
    "inputs": [
      {
        "internalType": "address",
        "name": "",
        "type": "address"
      },
      {
        "internalType": "address",
        "name": "",
        "type": "address"
      },
      {
        "internalType": "uint256[]",
        "name": "",
        "type": "uint256[]"
      },
      {
        "internalType": "uint256[]",
        "name": "",
        "type": "uint256[]"
      },
      {
        "internalType": "bytes",
        "name": "",
        "type": "bytes"
      }
    ],
    "name": "onERC1155BatchReceived",
    "outputs": [
      {
        "internalType": "bytes4",
        "name": "",
        "type": "bytes4"
      }
    ],
    "stateMutability": "nonpayable",
    "type": "function"
  },
  {
    "inputs": [
      {
        "internalType": "address",
        "name": "",
        "type": "address"
      },
      {
        "internalType": "address",
        "name": "",
        "type": "address"
      },
      {
        "internalType": "uint256",
        "name": "",
        "type": "uint256"
      },
      {
        "internalType": "uint256",
        "name": "",
        "type": "uint256"
      },
      {
        "internalType": "bytes",
        "name": "",
        "type": "bytes"
      }
    ],
    "name": "onERC1155Received",
    "outputs": [
      {
        "internalType": "bytes4",
        "name": "",
        "type": "bytes4"
      }
    ],
    "stateMutability": "nonpayable",
    "type": "function"
  },
  {
    "inputs": [],
    "name": "owner",
    "outputs": [
      {
        "internalType": "address",
        "name": "",
        "type": "address"
      }
    ],
    "stateMutability": "view",
    "type": "function"
  },
  {
    "inputs": [],
    "name": "renounceOwnership",
    "outputs": [],
    "stateMutability": "nonpayable",
    "type": "function"
  },
  {
    "inputs": [
      {
        "internalType": "uint256",
        "name": "chapterId",
        "type": "uint256"
      },
      {
        "internalType": "uint256[]",
        "name": "chapterOptionIds",
        "type": "uint256[]"
      }
    ],
    "name": "setChapterOptions",
    "outputs": [],
    "stateMutability": "nonpayable",
    "type": "function"
  },
  {
    "inputs": [
      {
        "internalType": "uint256[]",
        "name": "_chapters",
        "type": "uint256[]"
      }
    ],
    "name": "setChapters",
    "outputs": [],
    "stateMutability": "nonpayable",
    "type": "function"
  },
  {
    "inputs": [
      {
        "internalType": "address",
        "name": "_documentaryProducerPassContract",
        "type": "address"
      }
    ],
    "name": "setDocumentaryProducerPass",
    "outputs": [],
    "stateMutability": "nonpayable",
    "type": "function"
  },
  {
    "inputs": [
      {
        "internalType": "uint256",
        "name": "chapterId",
        "type": "uint256"
      },
      {
        "internalType": "bool",
        "name": "enabled",
        "type": "bool"
      }
    ],
    "name": "setVotingEnabledForChapter",
    "outputs": [],
    "stateMutability": "nonpayable",
    "type": "function"
  },
  {
    "inputs": [
      {
        "internalType": "uint256",
        "name": "chapterId",
        "type": "uint256"
      },
      {
        "internalType": "uint256",
        "name": "voteOptionId",
        "type": "uint256"
      },
      {
        "internalType": "uint256",
        "name": "amount",
        "type": "uint256"
      }
    ],
    "name": "stakeProducerPassAndVote",
    "outputs": [],
    "stateMutability": "nonpayable",
    "type": "function"
  },
  {
    "inputs": [
      {
        "internalType": "bytes4",
        "name": "interfaceId",
        "type": "bytes4"
      }
    ],
    "name": "supportsInterface",
    "outputs": [
      {
        "internalType": "bool",
        "name": "",
        "type": "bool"
      }
    ],
    "stateMutability": "view",
    "type": "function"
  },
  {
    "inputs": [
      {
        "internalType": "address",
        "name": "newOwner",
        "type": "address"
      }
    ],
    "name": "transferOwnership",
    "outputs": [],
    "stateMutability": "nonpayable",
    "type": "function"
  },
  {
    "inputs": [
      {
        "internalType": "uint256",
        "name": "chapterId",
        "type": "uint256"
      },
      {
        "internalType": "uint256",
        "name": "voteOptionId",
        "type": "uint256"
      }
    ],
    "name": "unstakeProducerPass",
    "outputs": [],
    "stateMutability": "nonpayable",
    "type": "function"
  },
  {
    "inputs": [
      {
        "internalType": "uint256",
        "name": "",
        "type": "uint256"
      }
    ],
    "name": "votingEnabledForChapter",
    "outputs": [
      {
        "internalType": "bool",
        "name": "",
        "type": "bool"
      }
    ],
    "stateMutability": "view",
    "type": "function"
  }
]
